tank/__init__.py
tank/bootstrap.py
tank/logging_conf.py
tank/main.py
tank/terraform_installer.py
tank/version.py
tank/controllers/__init__.py
tank/controllers/ansible.py
tank/controllers/base.py
tank/controllers/cluster.py
tank/core/__init__.py
tank/core/binding.py
tank/core/cloud_settings.py
tank/core/exc.py
tank/core/lambdas.py
tank/core/regions.py
tank/core/run.py
tank/core/testcase.py
tank/core/tf.py
tank/core/utils.py
tank/ext/__init__.py
tank/plugins/__init__.py
tank/resources/bindings.yml
tank/resources/regions.yml
tank/resources/testcase_schema.yml
tank/resources/ansible/ansible-requirements.yml
tank/resources/ansible/ansible.cfg
tank/resources/ansible/common.yml
tank/resources/ansible/core.yml
tank/resources/ansible/templates/ansible-report.json.j2
tank/resources/providers/digitalocean/backend.tf
tank/resources/providers/digitalocean/main.tf
tank/resources/providers/gce/backend.tf
tank/resources/providers/gce/main.tf
tank/resources/scripts/tank-packetloss
mixbytes_tank-1.0.2.dist-info/LICENSE
mixbytes_tank-1.0.2.dist-info/METADATA
mixbytes_tank-1.0.2.dist-info/WHEEL
mixbytes_tank-1.0.2.dist-info/entry_points.txt
mixbytes_tank-1.0.2.dist-info/top_level.txt
mixbytes_tank-1.0.2.dist-info/RECORD
