Metadata-Version: 2.1
Name: mixbytes-tank
Version: 1.0.2
Summary: Benchmark engine for blockchains
Home-page: https://github.com/mixbytes/tank/
Author: MixBytes LLC
Author-email: hello@mixbytes.io
License: Apache-2.0
Keywords: bench benchmark blockchain
Platform: UNKNOWN
Classifier: Development Status :: 3 - Alpha
Classifier: Environment :: Console
Classifier: Intended Audience :: Developers
Classifier: License :: OSI Approved :: Apache Software License
Classifier: Operating System :: POSIX :: Linux
Classifier: Operating System :: MacOS
Classifier: Topic :: Software Development :: Testing
Classifier: Topic :: System :: Benchmark
Classifier: Topic :: System :: Distributed Computing
Classifier: Topic :: System :: Clustering
Classifier: Programming Language :: Python :: 3
Classifier: Programming Language :: Python :: 3.7
Classifier: Programming Language :: Python :: 3 :: Only
Classifier: Programming Language :: Python :: Implementation :: CPython
Requires-Python: >=3
Requires-Dist: cement (==3.0.4)
Requires-Dist: ansible (>=2.8.0)
Requires-Dist: jinja2
Requires-Dist: pyyaml
Requires-Dist: colorlog
Requires-Dist: sh (==1.12.13)
Requires-Dist: jsonschema (==3.0.1)
Requires-Dist: filelock
Requires-Dist: tabulate (==0.8.3)
Requires-Dist: namesgenerator (==0.3)
